[
    {
        "uri": "https://alili.tech/archive/mrwjjr0ca4i/",
        "title": "2019年05月Github Javascript开源项目精选",
        "tags": ["Trending"],
        "description": ""
    },
    {
        "uri": "https://alili.tech/archive/3xwbcv1w21i/",
        "title": "前端微服务化进阶2 - 本地开发指南",
        "tags": ["微前端", "MicroFrontend", "前端架构"],
        "description": ""
    },
    {
        "uri": "https://alili.tech/archive/9xuojm75d2a/",
        "title": "前端微服务化进阶1 - 基于umi的子模块方案",
        "tags": ["微前端", "MicroFrontend", "前端架构"],
        "description": ""
    },
    {
        "uri": "https://alili.tech/archive/ol9qis0n8xe/",
        "title": "2019年04月Github Javascript开源项目精选",
        "tags": ["Trending"],
        "description": ""
    },
    {
        "uri": "https://alili.tech/archive/7815p445rtf/",
        "title": "记一次MongoDB迁移 - 备份与恢复",
        "tags": ["MongoDB"],
        "description": ""
    },
    {
        "uri": "https://alili.tech/archive/a5ficy1jp7n/",
        "title": "2019年03月Github Javascript开源项目精选",
        "tags": ["Trending"],
        "description": ""
    },
    {
        "uri": "https://alili.tech/archive/nyhmtbanv2e/",
        "title": "Alili Weekly 前端周刊 第二十一期",
        "tags": ["前端周刊", "Weekly"],
        "description": ""
    },
    {
        "uri": "https://alili.tech/archive/ixgdxkltl8/",
        "title": "Alili Weekly 前端周刊 第二十期",
        "tags": ["前端周刊", "Weekly"],
        "description": ""
    },
    {
        "uri": "https://alili.tech/archive/0b92giccynog/",
        "title": "2019年02月Github Javascript开源项目精选",
        "tags": ["Trending"],
        "description": ""
    },
    {
        "uri": "https://alili.tech/archive/9yqolmweou5/",
        "title": "Alili Weekly 前端周刊 第十九期",
        "tags": ["前端周刊", "Weekly"],
        "description": ""
    },
    {
        "uri": "https://alili.tech/archive/ggk866qh59i/",
        "title": "Alili Weekly 前端周刊 第十八期",
        "tags": ["前端周刊", "Weekly"],
        "description": ""
    },
    {
        "uri": "https://alili.tech/archive/nqs5fr7ddjn/",
        "title": "Alili Weekly 前端周刊 第十七期",
        "tags": ["前端周刊", "Weekly"],
        "description": ""
    },
    {
        "uri": "https://alili.tech/archive/zift8zkisnf/",
        "title": "一个两年前.gitattributes文件导致的bug",
        "tags": ["Git"],
        "description": ""
    },
    {
        "uri": "https://alili.tech/archive/an7l200dx1w/",
        "title": "LintCode 最长公共前缀",
        "tags": ["Leetcode"],
        "description": ""
    },
    {
        "uri": "https://alili.tech/archive/6kesofq8r0w/",
        "title": "Alili Weekly 前端周刊 第十六期",
        "tags": ["前端周刊", "Weekly"],
        "description": ""
    },
    {
        "uri": "https://alili.tech/archive/n15zv1hxje/",
        "title": "LintCode 买卖股票的最佳时机 II",
        "tags": ["Leetcode"],
        "description": ""
    },
    {
        "uri": "https://alili.tech/archive/k8ui524vul8/",
        "title": "Alili Weekly 前端周刊 第十五期",
        "tags": ["前端周刊", "Weekly"],
        "description": ""
    },
    {
        "uri": "https://alili.tech/archive/g6kghla5ugc/",
        "title": "Canvas 处理跨域图片终极方案",
        "tags": ["Javascript"],
        "description": ""
    },
    {
        "uri": "https://alili.tech/archive/rrc7ngyr5rp/",
        "title": "Git大小写不敏感导致的烦人问题",
        "tags": ["Git"],
        "description": ""
    },
    {
        "uri": "https://alili.tech/archive/ltucv5fyj9/",
        "title": "Visual Studio Code 下的 jsconfig.json",
        "tags": ["Visual Studio Code"],
        "description": ""
    },
    {
        "uri": "https://alili.tech/archive/gpjoaq9yztd/",
        "title": "2019年01月Github Javascript开源项目精选",
        "tags": ["Trending"],
        "description": ""
    },
    {
        "uri": "https://alili.tech/archive/0bx7k43lrexg/",
        "title": "Alili Weekly 前端周刊 第十四期",
        "tags": ["前端周刊", "Weekly"],
        "description": ""
    },
    {
        "uri": "https://alili.tech/archive/9rfliipfkip/",
        "title": "幕后英雄Abstract syntax tree抽象语法树",
        "tags": ["Javascript"],
        "description": ""
    },
    {
        "uri": "https://alili.tech/archive/53ogpu5lzuh/",
        "title": "2018 年终有感",
        "tags": ["年终总结"],
        "description": ""
    },
    {
        "uri": "https://alili.tech/archive/izbidk3gu3s/",
        "title": "聊聊HTTP的X-Forwarded-For 和 X-Real-IP",
        "tags": ["HTTP"],
        "description": ""
    },
    {
        "uri": "https://alili.tech/archive/g0um565bsaq/",
        "title": "Alili Weekly 前端周刊 第十三期",
        "tags": ["前端周刊", "Weekly"],
        "description": ""
    },
    {
        "uri": "https://alili.tech/archive/3u54dxnerfn/",
        "title": "Angular路径别名配置",
        "tags": ["Angular"],
        "description": ""
    },
    {
        "uri": "https://alili.tech/archive/ijfdh4ry66c/",
        "title": "Typescript的福音:Json To Interface",
        "tags": ["Typescript"],
        "description": ""
    },
    {
        "uri": "https://alili.tech/archive/cue4m2rioxl/",
        "title": "Centos7 如何使用yum升级git到最新版本",
        "tags": ["Linux"],
        "description": ""
    },
    {
        "uri": "https://alili.tech/archive/vtkyf54oda/",
        "title": "Alili Weekly 前端周刊 第十二期",
        "tags": ["前端周刊", "Weekly"],
        "description": ""
    },
    {
        "uri": "https://alili.tech/archive/cr8ze8vvvbw/",
        "title": "推荐一个Angular Electron 开箱即用的项目工程模板",
        "tags": ["Electron", "Angular"],
        "description": ""
    },
    {
        "uri": "https://alili.tech/archive/pw9ygknqvso/",
        "title": "Angular7 + Electron主进程与渲染进程通讯问题",
        "tags": ["Electron", "Angular"],
        "description": ""
    },
    {
        "uri": "https://alili.tech/archive/i15aswl1v4s/",
        "title": "从零搭建 Angular7 + Electron 桌面应用",
        "tags": ["Electron", "Angular"],
        "description": ""
    },
    {
        "uri": "https://alili.tech/archive/fva8fa69c4d/",
        "title": "Alili Weekly 前端周刊 第十一期",
        "tags": ["前端周刊", "Weekly"],
        "description": ""
    },
    {
        "uri": "https://alili.tech/archive/unui11c01ml/",
        "title": "记2018年最后一次前端分享(提供Slides)",
        "tags": ["Slides"],
        "description": ""
    },
    {
        "uri": "https://alili.tech/archive/zm2u9iewb9d/",
        "title": "2018年12月Github Javascript开源项目精选",
        "tags": ["Trending"],
        "description": ""
    },
    {
        "uri": "https://alili.tech/archive/dn3bpemyttp/",
        "title": "Alili Weekly 前端周刊 第十期",
        "tags": ["前端周刊", "Weekly"],
        "description": ""
    },
    {
        "uri": "https://alili.tech/archive/i9t0x2tvleo/",
        "title": "使用husky提升Code Review的效率",
        "tags": ["Code Review"],
        "description": ""
    },
    {
        "uri": "https://alili.tech/archive/1479pecm0mbo/",
        "title": "让团队保持Code Review习惯的三大法宝",
        "tags": ["Code Review"],
        "description": ""
    },
    {
        "uri": "https://alili.tech/archive/lywhtrtg9dm/",
        "title": "Alili Weekly 前端周刊 第九期",
        "tags": ["前端周刊", "Weekly"],
        "description": ""
    },
    {
        "uri": "https://alili.tech/archive/lbpnt17e1sc/",
        "title": "cheeriojs加载html时中文会默认解析成unicode的问题",
        "tags": ["Nodejs"],
        "description": ""
    },
    {
        "uri": "https://alili.tech/archive/sdwn0mwjjj8/",
        "title": "从前端角度来看声明式编程与命令式编程",
        "tags": ["Javascript"],
        "description": ""
    },
    {
        "uri": "https://alili.tech/archive/f16eaj0p4la/",
        "title": "Angular模板的安全导航( ?. )",
        "tags": ["Angular"],
        "description": ""
    },
    {
        "uri": "https://alili.tech/archive/l1gp8abhpha/",
        "title": "Alili Weekly 前端周刊 第八期",
        "tags": ["前端周刊", "Weekly"],
        "description": ""
    },
    {
        "uri": "https://alili.tech/archive/oj8dtatmwzg/",
        "title": "使用Travis CI自动化部署你的Hugo,Hexo博客",
        "tags": ["Hugo", "持续集成", "Travis", "Hexo"],
        "description": ""
    },
    {
        "uri": "https://alili.tech/archive/r5ibcpo557h/",
        "title": "让你的Hugo博客支持echarts图表",
        "tags": ["Hugo"],
        "description": ""
    },
    {
        "uri": "https://alili.tech/archive/yqufemb0c1m/",
        "title": "Hugo平台博文指定时间之后不显示?",
        "tags": ["Hugo"],
        "description": ""
    },
    {
        "uri": "https://alili.tech/archive/0xh05yxhj3yq/",
        "title": "Hugo博客百度SEO终极优化,熊掌号自动推送",
        "tags": ["Hugo", "SEO"],
        "description": ""
    },
    {
        "uri": "https://alili.tech/archive/vyetuiwpul/",
        "title": "Alili Weekly 前端周刊 第七期",
        "tags": ["前端周刊", "Weekly"],
        "description": ""
    },
    {
        "uri": "https://alili.tech/archive/obvozmdf/",
        "title": "博客构建工具Hugo的基本使用",
        "tags": ["Hugo"],
        "description": ""
    },
    {
        "uri": "https://alili.tech/archive/c38d0045/",
        "title": "Hexo Process Out of Memory 内存溢出问题",
        "tags": ["Hexo"],
        "description": ""
    },
    {
        "uri": "https://alili.tech/archive/cf2c83a/",
        "title": "Code Review工具推荐以及使用报告",
        "tags": ["Code Review"],
        "description": ""
    },
    {
        "uri": "https://alili.tech/archive/2c2b79f6/",
        "title": "Alili Weekly 前端周刊 第六期",
        "tags": ["前端周刊", "Weekly"],
        "description": ""
    },
    {
        "uri": "https://alili.tech/archive/e57d7fd7/",
        "title": "2018年11月Github Javascript开源项目精选",
        "tags": ["Trending"],
        "description": ""
    },
    {
        "uri": "https://alili.tech/archive/bbaf6d07/",
        "title": "如何通过 Code Review 帮助团队提升代码质量",
        "tags": ["Code Review"],
        "description": ""
    },
    {
        "uri": "https://alili.tech/archive/b8bdc73c/",
        "title": "升级Mac 10.14 mojave后辅助功能空白无法添加问题",
        "tags": ["mac"],
        "description": ""
    },
    {
        "uri": "https://alili.tech/archive/4925322f/",
        "title": "Alili Weekly 前端周刊 第五期",
        "tags": ["前端周刊", "Weekly"],
        "description": ""
    },
    {
        "uri": "https://alili.tech/archive/44b730cc/",
        "title": "2018年11月国内浏览器数据统计",
        "tags": ["数据分析"],
        "description": ""
    },
    {
        "uri": "https://alili.tech/archive/1a4f2dcf/",
        "title": "在Webpack与Systemjs中构建你的Single-SPA微前端应用",
        "tags": ["微前端", "MicroFrontend"],
        "description": ""
    },
    {
        "uri": "https://alili.tech/archive/22975f44/",
        "title": "Single-SPA微前端框架的使用Demo汇总",
        "tags": ["微前端", "MicroFrontend", "前端架构"],
        "description": ""
    },
    {
        "uri": "https://alili.tech/archive/ed854758/",
        "title": "Git删除所有提交记录解决方案",
        "tags": ["Git"],
        "description": ""
    },
    {
        "uri": "https://alili.tech/archive/26bbf768/",
        "title": "Alili Weekly 前端周刊 第四期",
        "tags": ["前端周刊", "Weekly"],
        "description": ""
    },
    {
        "uri": "https://alili.tech/archive/9d64fe09/",
        "title": "让你的Hexo博客支持熊掌号URL自动推送,百度24小时收录",
        "tags": ["SEO"],
        "description": ""
    },
    {
        "uri": "https://alili.tech/archive/84622ce5/",
        "title": "Nodejs爬虫技巧-使用Puppeteer下载图片或文件",
        "tags": ["puppeteer"],
        "description": ""
    },
    {
        "uri": "https://alili.tech/archive/9196ee0d/",
        "title": "Alili Weekly 前端周刊 第三期",
        "tags": ["前端周刊", "Weekly"],
        "description": ""
    },
    {
        "uri": "https://alili.tech/archive/b3ccb586/",
        "title": "任天堂Switch 6.0+ 系统菜单汉化",
        "tags": ["Game"],
        "description": ""
    },
    {
        "uri": "https://alili.tech/archive/150b3ba6/",
        "title": "Switch的NSP和XCI什么区别？",
        "tags": ["Game"],
        "description": ""
    },
    {
        "uri": "https://alili.tech/archive/dc884d5f/",
        "title": "Alili Weekly 前端周刊 第二期",
        "tags": ["前端周刊", "Weekly"],
        "description": ""
    },
    {
        "uri": "https://alili.tech/archive/33fa548c/",
        "title": "Nintendo Switch破解原理",
        "tags": ["Game"],
        "description": ""
    },
    {
        "uri": "https://alili.tech/archive/69a6fd18/",
        "title": "使用Eggjs(koa) &amp; web3.js开发你的以太坊Dapp",
        "tags": ["区块链"],
        "description": ""
    },
    {
        "uri": "https://alili.tech/archive/ec9ea187/",
        "title": "Alili Weekly 前端周刊 第一期",
        "tags": ["前端周刊", "Weekly"],
        "description": ""
    },
    {
        "uri": "https://alili.tech/archive/4a50d81d/",
        "title": "2018年10月国内浏览器数据统计",
        "tags": ["数据分析"],
        "description": ""
    },
    {
        "uri": "https://alili.tech/archive/66c1c154/",
        "title": "Centos7环境下启动Upsource失败解决办法",
        "tags": ["Upsource"],
        "description": ""
    },
    {
        "uri": "https://alili.tech/archive/df8d5e8d/",
        "title": "利用ngrok给你的机器打个洞 - 内网穿透",
        "tags": ["Network"],
        "description": ""
    },
    {
        "uri": "https://alili.tech/archive/f2c7a3e5/",
        "title": "2018年09月Github Javascript开源项目精选",
        "tags": ["Trending"],
        "description": ""
    },
    {
        "uri": "https://alili.tech/archive/ce685b9f/",
        "title": "前端微服务化解决方案8 - 二次构建",
        "tags": ["微前端", "MicroFrontend", "前端架构"],
        "description": ""
    },
    {
        "uri": "https://alili.tech/archive/5e00e43d/",
        "title": "前端微服务化解决方案7 - 静态数据共享",
        "tags": ["微前端", "MicroFrontend", "前端架构"],
        "description": ""
    },
    {
        "uri": "https://alili.tech/archive/ffb0c5ab/",
        "title": "前端微服务化解决方案6 - 构建与部署",
        "tags": ["微前端", "MicroFrontend", "前端架构"],
        "description": ""
    },
    {
        "uri": "https://alili.tech/archive/5ff0b366/",
        "title": "前端微服务化解决方案5 - 路由分发",
        "tags": ["微前端", "MicroFrontend", "前端架构"],
        "description": ""
    },
    {
        "uri": "https://alili.tech/archive/a9a1f81b/",
        "title": "前端微服务化解决方案4 - 消息总线",
        "tags": ["微前端", "MicroFrontend", "前端架构"],
        "description": ""
    },
    {
        "uri": "https://alili.tech/archive/1a60cede/",
        "title": "前端微服务化解决方案3 - 模块加载器",
        "tags": ["微前端", "MicroFrontend", "前端架构"],
        "description": ""
    },
    {
        "uri": "https://alili.tech/archive/11052bf4/",
        "title": "前端微服务化解决方案2 - Single-SPA",
        "tags": ["微前端", "MicroFrontend", "前端架构"],
        "description": ""
    },
    {
        "uri": "https://alili.tech/archive/ea599f7c/",
        "title": "前端微服务化解决方案1 - 思考",
        "tags": ["微前端", "MicroFrontend", "前端架构"],
        "description": ""
    },
    {
        "uri": "https://alili.tech/archive/c25273ee/",
        "title": "2018年09月国内浏览器数据统计",
        "tags": ["数据分析"],
        "description": ""
    },
    {
        "uri": "https://alili.tech/archive/ef96a5b6/",
        "title": "Network笔记整理 - 网络协议与网络分层",
        "tags": ["Network"],
        "description": ""
    },
    {
        "uri": "https://alili.tech/archive/c4353316/",
        "title": "2018年08月Github Javascript开源项目精选",
        "tags": ["Trending"],
        "description": ""
    },
    {
        "uri": "https://alili.tech/archive/3f6742b1/",
        "title": "Linux -  Centos 时区设置",
        "tags": ["Linux"],
        "description": ""
    },
    {
        "uri": "https://alili.tech/archive/280d4016/",
        "title": "2018年07月Github Javascript开源项目精选",
        "tags": ["Trending"],
        "description": ""
    },
    {
        "uri": "https://alili.tech/archive/1effd0e5/",
        "title": "2018年06月Github Javascript开源项目精选",
        "tags": ["Trending"],
        "description": ""
    },
    {
        "uri": "https://alili.tech/archive/c165a1d9/",
        "title": "MongoDB - 在Egg中使用MondoDB",
        "tags": ["MongoDB"],
        "description": ""
    },
    {
        "uri": "https://alili.tech/archive/311875a2/",
        "title": "MongoDB - 文档的基本操作 (二)",
        "tags": ["MongoDB"],
        "description": ""
    },
    {
        "uri": "https://alili.tech/archive/9e29eec0/",
        "title": "MongoDB - 文档的基本操作 (一)",
        "tags": ["MongoDB"],
        "description": ""
    },
    {
        "uri": "https://alili.tech/archive/3a26a4b/",
        "title": "MongoDB - 数据库与集合的基本操作",
        "tags": ["MongoDB"],
        "description": ""
    },
    {
        "uri": "https://alili.tech/archive/1f77f611/",
        "title": "MongoDB - 基本概念与其他数据库对比",
        "tags": ["MongoDB"],
        "description": ""
    },
    {
        "uri": "https://alili.tech/archive/f82d8042/",
        "title": "MongoDB - 安装与启动",
        "tags": ["MongoDB"],
        "description": ""
    },
    {
        "uri": "https://alili.tech/archive/45e861f0/",
        "title": "2018年05月Github Javascript开源项目精选",
        "tags": ["Trending"],
        "description": ""
    },
    {
        "uri": "https://alili.tech/archive/b75b18ec/",
        "title": "以太坊开发之搭建宠物商店",
        "tags": ["区块链"],
        "description": ""
    },
    {
        "uri": "https://alili.tech/archive/ecce3d6/",
        "title": "以太坊开发之Solidity初学者的编辑器 -- remix-ide",
        "tags": ["区块链"],
        "description": ""
    },
    {
        "uri": "https://alili.tech/archive/bc28cb6c/",
        "title": "以太坊开发之一切从脚手架truffle开始",
        "tags": ["区块链"],
        "description": ""
    },
    {
        "uri": "https://alili.tech/archive/9713e794/",
        "title": "使用verdaccio搭建更加简单的私有npm服务器",
        "tags": ["Nodejs"],
        "description": ""
    },
    {
        "uri": "https://alili.tech/archive/629795fd/",
        "title": "Git push卡住解决办法",
        "tags": ["Git"],
        "description": ""
    },
    {
        "uri": "https://alili.tech/archive/731af103/",
        "title": "2018年04月Github Javascript开源项目精选",
        "tags": ["Trending"],
        "description": ""
    },
    {
        "uri": "https://alili.tech/archive/a5e195cc/",
        "title": "Linux -  SSH连接远程服务器直接执行command时PATH不全解决方案",
        "tags": ["Linux"],
        "description": ""
    },
    {
        "uri": "https://alili.tech/archive/f3c703da/",
        "title": "2018年03月Github Javascript开源项目精选",
        "tags": ["Trending"],
        "description": ""
    },
    {
        "uri": "https://alili.tech/archive/e550825/",
        "title": "Centos7环境下启动puppeteer失败解决办法",
        "tags": ["puppeteer"],
        "description": ""
    },
    {
        "uri": "https://alili.tech/archive/c5359329/",
        "title": "2018年02月Github Javascript开源项目精选",
        "tags": ["Trending"],
        "description": ""
    },
    {
        "uri": "https://alili.tech/archive/7f7747d0/",
        "title": "Linux - vim vi学习笔记",
        "tags": ["Linux"],
        "description": ""
    },
    {
        "uri": "https://alili.tech/archive/d150fc3c/",
        "title": "Linux - 安装nginx步骤",
        "tags": ["Linux"],
        "description": ""
    },
    {
        "uri": "https://alili.tech/archive/b9985e69/",
        "title": "一个没有界面的Chrome浏览器：puppeteer",
        "tags": ["puppeteer"],
        "description": ""
    },
    {
        "uri": "https://alili.tech/archive/fba46182/",
        "title": "基于shipit-deploy实现的多服务器自动化部署方案",
        "tags": ["Nodejs"],
        "description": ""
    },
    {
        "uri": "https://alili.tech/archive/5f4cf684/",
        "title": "Linux -  使用ssh-copy-id命令实现ssh Linux免密码登陆",
        "tags": ["Linux"],
        "description": ""
    },
    {
        "uri": "https://alili.tech/archive/a8ce80b/",
        "title": "开启Express，Egg.js，Koa.js 的Gzip模式",
        "tags": ["Nodejs"],
        "description": ""
    },
    {
        "uri": "https://alili.tech/archive/408ec5a5/",
        "title": "2017年12月Github Javascript开源项目精选",
        "tags": ["Trending"],
        "description": ""
    },
    {
        "uri": "https://alili.tech/archive/6eff5ac9/",
        "title": "Apache,Nginx,Express,Egg.js 支持前端HTML5 History 模式",
        "tags": ["Nodejs"],
        "description": ""
    },
    {
        "uri": "https://alili.tech/archive/524de824/",
        "title": "Egg.js 如何支持单页面应用",
        "tags": ["Nodejs"],
        "description": ""
    },
    {
        "uri": "https://alili.tech/archive/7cb6734b/",
        "title": "在自己搭建的cnpm发布公司私有代码",
        "tags": ["Nodejs"],
        "description": ""
    },
    {
        "uri": "https://alili.tech/archive/eed8d24e/",
        "title": "在公司搭建私有的cnpm服务器",
        "tags": ["Nodejs"],
        "description": ""
    },
    {
        "uri": "https://alili.tech/archive/b36fefc7/",
        "title": "Visual Studio Code隐藏从ts生成的额外js与map文件",
        "tags": ["Nodejs"],
        "description": ""
    },
    {
        "uri": "https://alili.tech/archive/1b9974b0/",
        "title": "2017年11月Github Javascript开源项目精选",
        "tags": ["Trending"],
        "description": ""
    },
    {
        "uri": "https://alili.tech/archive/153fb3f5/",
        "title": "让Visual Studio Code按照ESLint规则格式化你的代码",
        "tags": ["React"],
        "description": ""
    },
    {
        "uri": "https://alili.tech/archive/b3d50314/",
        "title": "Redux先放一边,开启MobX的新玩法",
        "tags": ["React"],
        "description": ""
    },
    {
        "uri": "https://alili.tech/archive/a280911b/",
        "title": "在你的React项目中使用Decorator 装饰器",
        "tags": ["React"],
        "description": ""
    },
    {
        "uri": "https://alili.tech/archive/638cc3cd/",
        "title": "Git系列之关于add命令的一些事",
        "tags": ["Git"],
        "description": ""
    },
    {
        "uri": "https://alili.tech/archive/7aed82f9/",
        "title": "React系列之父组件如何传递Props给this.props.children",
        "tags": ["React"],
        "description": ""
    },
    {
        "uri": "https://alili.tech/archive/53fea45f/",
        "title": "2017年09月Github Javascript开源项目精选",
        "tags": ["Trending"],
        "description": ""
    },
    {
        "uri": "https://alili.tech/archive/49f93461/",
        "title": "MySQL的安全模式",
        "tags": ["Database"],
        "description": ""
    },
    {
        "uri": "https://alili.tech/archive/78cba2eb/",
        "title": "MySQL的Access denied for user问题",
        "tags": ["Database"],
        "description": ""
    },
    {
        "uri": "https://alili.tech/archive/650c34ac/",
        "title": "2017年08月Github Javascript开源项目精选",
        "tags": ["Trending"],
        "description": ""
    },
    {
        "uri": "https://alili.tech/archive/bd292cd9/",
        "title": "利用Chrome DevTools调试Node.js",
        "tags": ["Nodejs"],
        "description": ""
    },
    {
        "uri": "https://alili.tech/archive/bb62bab9/",
        "title": "React系列之用create-react-native-app创建React Native应用",
        "tags": ["React"],
        "description": ""
    },
    {
        "uri": "https://alili.tech/archive/3b54e2d1/",
        "title": "聊聊HTTP的MIME",
        "tags": ["HTTP"],
        "description": ""
    },
    {
        "uri": "https://alili.tech/archive/84afbeeb/",
        "title": "HTTP的URI格式说明",
        "tags": ["HTTP"],
        "description": ""
    },
    {
        "uri": "https://alili.tech/archive/5e4dd5b8/",
        "title": "让Webpack支持sftp上传文件",
        "tags": ["Webpack"],
        "description": ""
    },
    {
        "uri": "https://alili.tech/archive/b4301d9b/",
        "title": "React系列之分享一个自适应高的iframe组件",
        "tags": ["React"],
        "description": ""
    },
    {
        "uri": "https://alili.tech/archive/a8e3f4c2/",
        "title": "Macbook Pro蓝牙不可用问题",
        "tags": ["mac"],
        "description": ""
    },
    {
        "uri": "https://alili.tech/archive/dd233b37/",
        "title": "发布基于nodejs的阿里云API签名生成工具 -- AliToSing",
        "tags": ["Nodejs"],
        "description": ""
    },
    {
        "uri": "https://alili.tech/archive/3b5f5a23/",
        "title": "React系列之让create-react-app支持导入less",
        "tags": ["React"],
        "description": ""
    },
    {
        "uri": "https://alili.tech/archive/10fba257/",
        "title": "React系列之JSX",
        "tags": ["React"],
        "description": ""
    },
    {
        "uri": "https://alili.tech/archive/7a6daf6e/",
        "title": "React系列之从一个脚手架开始说起:create-react-app",
        "tags": ["React"],
        "description": ""
    },
    {
        "uri": "https://alili.tech/archive/99619c4e/",
        "title": "npm、yarn包管理工具切换淘宝源",
        "tags": ["Nodejs"],
        "description": ""
    },
    {
        "uri": "https://alili.tech/archive/b0bb249b/",
        "title": "跨域还可以这样玩,使用CSS3特性做跨域",
        "tags": ["Javascript"],
        "description": ""
    },
    {
        "uri": "https://alili.tech/archive/4c861783/",
        "title": "Object.defineProperty与Proxy的共同之处",
        "tags": ["Javascript"],
        "description": ""
    },
    {
        "uri": "https://alili.tech/archive/9ca26edd/",
        "title": "聊聊Vue.js的事件修饰符",
        "tags": ["Vue"],
        "description": ""
    },
    {
        "uri": "https://alili.tech/archive/613bb601/",
        "title": "一个关于微信SPA页面webview的缓存问题",
        "tags": ["Angularjs"],
        "description": ""
    },
    {
        "uri": "https://alili.tech/archive/e25431a8/",
        "title": "Hexo的DTraceProviderBindings MODULE_NOT_FOUND问题",
        "tags": ["Hexo"],
        "description": ""
    },
    {
        "uri": "https://alili.tech/archive/e06698c9/",
        "title": "Express设置CORS,让浏览器可以跨域访问你的服务器",
        "tags": ["Nodejs"],
        "description": ""
    },
    {
        "uri": "https://alili.tech/archive/5bc12a97/",
        "title": "让Nodejs像浏览器一样Fetch你想要的",
        "tags": ["Nodejs"],
        "description": ""
    },
    {
        "uri": "https://alili.tech/archive/59cf5417/",
        "title": "Nodejs之http模块的get与post请求",
        "tags": ["Nodejs"],
        "description": ""
    },
    {
        "uri": "https://alili.tech/archive/cdd27771/",
        "title": "利用Nodejs获取公网IP",
        "tags": ["Nodejs"],
        "description": ""
    },
    {
        "uri": "https://alili.tech/archive/ff76a1bd/",
        "title": "基于Github与Coding等代码托管平台的自动化部署",
        "tags": ["Nodejs"],
        "description": ""
    },
    {
        "uri": "https://alili.tech/archive/7cafffa9/",
        "title": "利用Nodejs生成阿里云API签名",
        "tags": ["Nodejs"],
        "description": ""
    },
    {
        "uri": "https://alili.tech/archive/760c8e37/",
        "title": "关闭Mac系统的SIP与卸载Mac上的输入法",
        "tags": ["mac"],
        "description": ""
    },
    {
        "uri": "https://alili.tech/archive/4befbcf0/",
        "title": "Raspberry之时间自动校准",
        "tags": ["Raspberry Pi"],
        "description": ""
    },
    {
        "uri": "https://alili.tech/archive/b50a8cab/",
        "title": "POST请求要比GET安全吗",
        "tags": ["Javascript"],
        "description": ""
    },
    {
        "uri": "https://alili.tech/archive/9b723d04/",
        "title": "Raspberry之开机启动pm2",
        "tags": ["Raspberry Pi"],
        "description": ""
    },
    {
        "uri": "https://alili.tech/archive/58ab432d/",
        "title": "Raspberry之安装Nodejs",
        "tags": ["Raspberry Pi"],
        "description": ""
    },
    {
        "uri": "https://alili.tech/archive/8ad4a3a8/",
        "title": "Raspberry之外网访问树莓派",
        "tags": ["Raspberry Pi"],
        "description": ""
    },
    {
        "uri": "https://alili.tech/archive/467ebcb2/",
        "title": "Raspberry之利用SSH操作树莓派",
        "tags": ["Raspberry Pi"],
        "description": ""
    },
    {
        "uri": "https://alili.tech/archive/2a0d2aea/",
        "title": "Raspberry之系统安装",
        "tags": ["Raspberry Pi"],
        "description": ""
    },
    {
        "uri": "https://alili.tech/archive/cb56039f/",
        "title": "关于我在工作中项目调试的方法",
        "tags": ["Javascript"],
        "description": ""
    },
    {
        "uri": "https://alili.tech/archive/95852f7d/",
        "title": "我也写一个Canvas惊悚的粒子效果",
        "tags": ["Javascript"],
        "description": ""
    },
    {
        "uri": "https://alili.tech/archive/c36fa5ee/",
        "title": "置换与非置换元素",
        "tags": ["HTML"],
        "description": ""
    },
    {
        "uri": "https://alili.tech/archive/6e692504/",
        "title": "Javascript的运算符优先级",
        "tags": ["Javascript"],
        "description": ""
    },
    {
        "uri": "https://alili.tech/archive/d82a6654/",
        "title": "fetch遇到了一个坑",
        "tags": [],
        "description": ""
    },
    {
        "uri": "https://alili.tech/archive/e8e7fab1/",
        "title": "关于HTML5 History API",
        "tags": ["Javascript"],
        "description": ""
    },
    {
        "uri": "https://alili.tech/archive/3f5c7ee8/",
        "title": "关于FormData文件上传",
        "tags": [],
        "description": ""
    },
    {
        "uri": "https://alili.tech/archive/f9c22b08/",
        "title": "Angularjs的按需加载(3)",
        "tags": ["Angularjs"],
        "description": ""
    },
    {
        "uri": "https://alili.tech/archive/e0d91a49/",
        "title": "Angularjs的按需加载(2)",
        "tags": ["Angularjs"],
        "description": ""
    },
    {
        "uri": "https://alili.tech/archive/cbf4498a/",
        "title": "Angularjs的按需加载(1)",
        "tags": ["Angularjs"],
        "description": ""
    },
    {
        "uri": "https://alili.tech/archive/7abff3e/",
        "title": "Journey",
        "tags": [],
        "description": ""
    },
    {
        "uri": "https://alili.tech/about/",
        "title": "About Me",
        "tags": [],
        "description": ""
    },
    {
        "uri": "https://alili.tech/about/_resume/",
        "title": "个人简历",
        "tags": [],
        "description": ""
    },
    {
        "uri": "https://alili.tech/secret/",
        "title": "归档",
        "tags": [],
        "description": ""
    },
    {
        "uri": "https://alili.tech/archive/1e2d080b/",
        "title": "微信浏览器动态修改Title",
        "tags": ["weChat"],
        "description": ""
    },
    {
        "uri": "https://alili.tech/archive/7807a0b7/",
        "title": "Javascript的奇淫技巧",
        "tags": ["Javascript"],
        "description": ""
    },
    {
        "uri": "https://alili.tech/archive/884e3459/",
        "title": "浏览器常用的本地储存方式",
        "tags": ["Javascript"],
        "description": ""
    },
    {
        "uri": "https://alili.tech/archive/45db7962/",
        "title": "什么是浏览器的重绘与回流",
        "tags": ["HTML"],
        "description": ""
    },
    {
        "uri": "https://alili.tech/archive/cfcdda3/",
        "title": "移动端网站点击出现闪动或灰色背景问题",
        "tags": ["css"],
        "description": ""
    },
    {
        "uri": "https://alili.tech/archive/41effd04/",
        "title": "源码分析Angularjs中的Provider们的小小区别",
        "tags": ["Angularjs"],
        "description": ""
    },
    {
        "uri": "https://alili.tech/archive/4105a341/",
        "title": "Hexo的SEO优化(搜索引擎优化)",
        "tags": ["SEO"],
        "description": ""
    },
    {
        "uri": "https://alili.tech/archive/46973069/",
        "title": "ECMAScript 6 之Proxy",
        "tags": [],
        "description": ""
    },
    {
        "uri": "https://alili.tech/archive/91140f15/",
        "title": "ECMAScript 6 之Promise",
        "tags": [],
        "description": ""
    },
    {
        "uri": "https://alili.tech/archive/be827185/",
        "title": "ECMAScript 6 之Generator",
        "tags": [],
        "description": ""
    },
    {
        "uri": "https://alili.tech/archive/918f85ad/",
        "title": "ECMAScript 6 之箭头函数",
        "tags": [],
        "description": ""
    },
    {
        "uri": "https://alili.tech/archive/8d0689eb/",
        "title": "ECMAScript 6 之解构赋值",
        "tags": [],
        "description": ""
    },
    {
        "uri": "https://alili.tech/archive/573a0170/",
        "title": "ECMAScript 6 之变量那些事",
        "tags": [],
        "description": ""
    },
    {
        "uri": "https://alili.tech/archive/8bb9cbf7/",
        "title": "ECMAScript 6 之如何快速的做ES6练习",
        "tags": [],
        "description": ""
    },
    {
        "uri": "https://alili.tech/archive/20901007/",
        "title": "自动化部署前端代码 - grunt-ftp-deploy的使用",
        "tags": ["持续集成"],
        "description": ""
    },
    {
        "uri": "https://alili.tech/archive/c38cfa0d/",
        "title": "烦人的Angularjs注解 - grunt-ng-annotate的使用",
        "tags": ["Angularjs", "持续集成"],
        "description": ""
    },
    {
        "uri": "https://alili.tech/archive/baa7d23b/",
        "title": "Angularjs 指令模版",
        "tags": ["Angularjs"],
        "description": ""
    },
    {
        "uri": "https://alili.tech/archive/b585e161/",
        "title": "新的开始,心路历程",
        "tags": [],
        "description": ""
    },
    {
        "uri": "https://alili.tech/",
        "title": "Alili",
        "tags": [],
        "description": ""
    },
    {
        "uri": "https://alili.tech/tags/angular/",
        "title": "Angular",
        "tags": [],
        "description": ""
    },
    {
        "uri": "https://alili.tech/tags/angularjs/",
        "title": "Angularjs",
        "tags": [],
        "description": ""
    },
    {
        "uri": "https://alili.tech/archive/",
        "title": "Archives",
        "tags": [],
        "description": ""
    },
    {
        "uri": "https://alili.tech/categories/",
        "title": "Categories",
        "tags": [],
        "description": ""
    },
    {
        "uri": "https://alili.tech/tags/code-review/",
        "title": "Code Review",
        "tags": [],
        "description": ""
    },
    {
        "uri": "https://alili.tech/tags/css/",
        "title": "Css",
        "tags": [],
        "description": ""
    },
    {
        "uri": "https://alili.tech/tags/database/",
        "title": "Database",
        "tags": [],
        "description": ""
    },
    {
        "uri": "https://alili.tech/tags/electron/",
        "title": "Electron",
        "tags": [],
        "description": ""
    },
    {
        "uri": "https://alili.tech/tags/game/",
        "title": "Game",
        "tags": [],
        "description": ""
    },
    {
        "uri": "https://alili.tech/tags/git/",
        "title": "Git",
        "tags": [],
        "description": ""
    },
    {
        "uri": "https://alili.tech/tags/hexo/",
        "title": "Hexo",
        "tags": [],
        "description": ""
    },
    {
        "uri": "https://alili.tech/tags/html/",
        "title": "Html",
        "tags": [],
        "description": ""
    },
    {
        "uri": "https://alili.tech/tags/http/",
        "title": "Http",
        "tags": [],
        "description": ""
    },
    {
        "uri": "https://alili.tech/tags/hugo/",
        "title": "Hugo",
        "tags": [],
        "description": ""
    },
    {
        "uri": "https://alili.tech/tags/javascript/",
        "title": "Javascript",
        "tags": [],
        "description": ""
    },
    {
        "uri": "https://alili.tech/tags/leetcode/",
        "title": "Leetcode",
        "tags": [],
        "description": ""
    },
    {
        "uri": "https://alili.tech/tags/linux/",
        "title": "Linux",
        "tags": [],
        "description": ""
    },
    {
        "uri": "https://alili.tech/tags/mac/",
        "title": "Mac",
        "tags": [],
        "description": ""
    },
    {
        "uri": "https://alili.tech/tags/microfrontend/",
        "title": "Microfrontend",
        "tags": [],
        "description": ""
    },
    {
        "uri": "https://alili.tech/tags/mongodb/",
        "title": "Mongodb",
        "tags": [],
        "description": ""
    },
    {
        "uri": "https://alili.tech/tags/network/",
        "title": "Network",
        "tags": [],
        "description": ""
    },
    {
        "uri": "https://alili.tech/tags/nodejs/",
        "title": "Nodejs",
        "tags": [],
        "description": ""
    },
    {
        "uri": "https://alili.tech/tags/puppeteer/",
        "title": "Puppeteer",
        "tags": [],
        "description": ""
    },
    {
        "uri": "https://alili.tech/tags/raspberry-pi/",
        "title": "Raspberry Pi",
        "tags": [],
        "description": ""
    },
    {
        "uri": "https://alili.tech/tags/react/",
        "title": "React",
        "tags": [],
        "description": ""
    },
    {
        "uri": "https://alili.tech/tags/seo/",
        "title": "Seo",
        "tags": [],
        "description": ""
    },
    {
        "uri": "https://alili.tech/tags/slides/",
        "title": "Slides",
        "tags": [],
        "description": ""
    },
    {
        "uri": "https://alili.tech/tags/",
        "title": "Tags",
        "tags": [],
        "description": ""
    },
    {
        "uri": "https://alili.tech/tags/travis/",
        "title": "Travis",
        "tags": [],
        "description": ""
    },
    {
        "uri": "https://alili.tech/tags/trending/",
        "title": "Trending",
        "tags": [],
        "description": ""
    },
    {
        "uri": "https://alili.tech/tags/typescript/",
        "title": "Typescript",
        "tags": [],
        "description": ""
    },
    {
        "uri": "https://alili.tech/tags/upsource/",
        "title": "Upsource",
        "tags": [],
        "description": ""
    },
    {
        "uri": "https://alili.tech/tags/visual-studio-code/",
        "title": "Visual Studio Code",
        "tags": [],
        "description": ""
    },
    {
        "uri": "https://alili.tech/tags/vue/",
        "title": "Vue",
        "tags": [],
        "description": ""
    },
    {
        "uri": "https://alili.tech/tags/webpack/",
        "title": "Webpack",
        "tags": [],
        "description": ""
    },
    {
        "uri": "https://alili.tech/tags/wechat/",
        "title": "Wechat",
        "tags": [],
        "description": ""
    },
    {
        "uri": "https://alili.tech/tags/weekly/",
        "title": "Weekly",
        "tags": [],
        "description": ""
    },
    {
        "uri": "https://alili.tech/tags/%E5%89%8D%E7%AB%AF%E5%91%A8%E5%88%8A/",
        "title": "前端周刊",
        "tags": [],
        "description": ""
    },
    {
        "uri": "https://alili.tech/tags/%E5%89%8D%E7%AB%AF%E6%9E%B6%E6%9E%84/",
        "title": "前端架构",
        "tags": [],
        "description": ""
    },
    {
        "uri": "https://alili.tech/tags/%E5%8C%BA%E5%9D%97%E9%93%BE/",
        "title": "区块链",
        "tags": [],
        "description": ""
    },
    {
        "uri": "https://alili.tech/tags/%E5%B9%B4%E7%BB%88%E6%80%BB%E7%BB%93/",
        "title": "年终总结",
        "tags": [],
        "description": ""
    },
    {
        "uri": "https://alili.tech/tags/%E5%BE%AE%E5%89%8D%E7%AB%AF/",
        "title": "微前端",
        "tags": [],
        "description": ""
    },
    {
        "uri": "https://alili.tech/tags/%E6%8C%81%E7%BB%AD%E9%9B%86%E6%88%90/",
        "title": "持续集成",
        "tags": [],
        "description": ""
    },
    {
        "uri": "https://alili.tech/tags/%E6%95%B0%E6%8D%AE%E5%88%86%E6%9E%90/",
        "title": "数据分析",
        "tags": [],
        "description": ""
    }]